smoltoolbox/__init__.py
smoltoolbox-0.0.0.dist-info/METADATA
smoltoolbox-0.0.0.dist-info/WHEEL
smoltoolbox-0.0.0.dist-info/top_level.txt
smoltoolbox-0.0.0.dist-info/RECORD
