Metadata-Version: 2.4
Name: smoltoolbox
Version: 0.0.0
Summary: A small and probably useless toolbox
Author-email: Your Name <you@example.com>
License: MIT
Project-URL: Homepage, https://github.com/yourusername/smoltoolbox
Requires-Python: >=3.7
